docp_parsers/__init__.py
docp_parsers/libs/_version.py
docp_parsers/libs/changelog.py
docp_parsers/objects/__init__.py
docp_parsers/objects/_docbaseobject.py
docp_parsers/objects/_imgobject.py
docp_parsers/objects/_pageobject.py
docp_parsers/objects/_slideobject.py
docp_parsers/objects/_tableobject.py
docp_parsers/objects/pdfobject.py
docp_parsers/objects/pptxobject.py
docp_parsers/parsers/__init__.py
docp_parsers/parsers/_pdfbaseparser.py
docp_parsers/parsers/_pdftableparser.py
docp_parsers/parsers/_pdftextparser.py
docp_parsers/parsers/_pptxbaseparser.py
docp_parsers/parsers/_pptxtextparser.py
docp_parsers/parsers/pdfparser.py
docp_parsers/parsers/pptxparser.py
docp_parsers/parsers/putilities.py
docp_parsers-1.0.0.dist-info/licenses/LICENSE
docp_parsers-1.0.0.dist-info/METADATA
docp_parsers-1.0.0.dist-info/WHEEL
docp_parsers-1.0.0.dist-info/top_level.txt
docp_parsers-1.0.0.dist-info/RECORD
